Metadata-Version: 1.0
Name: mf-client
Version: 0.0.4
Summary: mf_client
Home-page: UNKNOWN
Author: Aaron Phillips (University of Salford)
Author-email: a.phillips3@edu.salford.ac.uk
License: Apache License (2.0)
Platform: UNKNOWN
